<?xml version="1.0" encoding="utf-8"?>
<!DOCTYPE hibernate-mapping PUBLIC "-//Hibernate/Hibernate Mapping DTD 3.0//EN"
"http://hibernate.sourceforge.net/hibernate-mapping-3.0.dtd">
<!-- 
    Mapping file autogenerated by MyEclipse Persistence Tools
-->
<hibernate-mapping>
    <class name="com.ibs.hibernate.bean.ord.Order" table="ibs_Order" lazy="false">
    		<id name="orderNo"  column="order_no" type="string">
    		</id>
    		<property name="userNo" column="user_No" type="integer"></property>
    		<property name="orderDate" column="order_Date" type="date"></property>
    		<property name="orderTime" column="order_Time" type="time"></property>
    		<property name="phone" column="phone" type="string" length="11"></property>
    </class>
</hibernate-mapping>
